int3/__init__.py
int3/__main__.py
int3/_utils.py
int3/errors.py
int3/version.py
int3/_vendored/__init__.py
int3/_vendored/llvmlite/__init__.py
int3/_vendored/llvmlite/_version.py
int3/_vendored/llvmlite/utils.py
int3/_vendored/llvmlite/binding/__init__.py
int3/_vendored/llvmlite/binding/analysis.py
int3/_vendored/llvmlite/binding/common.py
int3/_vendored/llvmlite/binding/context.py
int3/_vendored/llvmlite/binding/dylib.py
int3/_vendored/llvmlite/binding/executionengine.py
int3/_vendored/llvmlite/binding/ffi.py
int3/_vendored/llvmlite/binding/initfini.py
int3/_vendored/llvmlite/binding/libllvmlite.so
int3/_vendored/llvmlite/binding/linker.py
int3/_vendored/llvmlite/binding/module.py
int3/_vendored/llvmlite/binding/newpassmanagers.py
int3/_vendored/llvmlite/binding/object_file.py
int3/_vendored/llvmlite/binding/options.py
int3/_vendored/llvmlite/binding/orcjit.py
int3/_vendored/llvmlite/binding/passmanagers.py
int3/_vendored/llvmlite/binding/targets.py
int3/_vendored/llvmlite/binding/transforms.py
int3/_vendored/llvmlite/binding/typeref.py
int3/_vendored/llvmlite/binding/value.py
int3/_vendored/llvmlite/ir/__init__.py
int3/_vendored/llvmlite/ir/_utils.py
int3/_vendored/llvmlite/ir/builder.py
int3/_vendored/llvmlite/ir/context.py
int3/_vendored/llvmlite/ir/instructions.py
int3/_vendored/llvmlite/ir/module.py
int3/_vendored/llvmlite/ir/transforms.py
int3/_vendored/llvmlite/ir/types.py
int3/_vendored/llvmlite/ir/values.py
int3/_vendored/llvmlite/tests/__init__.py
int3/_vendored/llvmlite/tests/__main__.py
int3/_vendored/llvmlite/tests/customize.py
int3/_vendored/llvmlite/tests/refprune_proto.py
int3/_vendored/llvmlite/tests/test_binding.py
int3/_vendored/llvmlite/tests/test_ir.py
int3/_vendored/llvmlite/tests/test_refprune.py
int3/_vendored/llvmlite/tests/test_valuerepr.py
int3/architecture/__init__.py
int3/architecture/architecture.py
int3/architecture/endian.py
int3/architecture/instruction_width.py
int3-0.0.2.dist-info/METADATA
int3-0.0.2.dist-info/WHEEL
int3-0.0.2.dist-info/entry_points.txt
int3-0.0.2.dist-info/top_level.txt
int3-0.0.2.dist-info/RECORD
int3-0.0.2.dist-info/licenses/LICENSE.txt
