Metadata-Version: 2.4
Name: int3
Version: 0.0.2
Summary: Compiler for position-independent assembly programs
Author-email: Brian Welch <12776611+welchbj@users.noreply.github.com>
Maintainer-email: Brian Welch <12776611+welchbj@users.noreply.github.com>
License-Expression: LGPL-3.0-only
Project-URL: Homepage, https://github.com/welchbj/int3
Project-URL: Documentation, https://int3.readthedocs.io
Project-URL: Repository, https://github.com/welchbj/int3
Project-URL: Bug Tracker, https://github.com/welchbj/int3/issues
Keywords: assembly,llvm,compiler
Classifier: Environment :: Console
Classifier: Operating System :: POSIX
Classifier: Programming Language :: Python :: Implementation :: CPython
Classifier: Programming Language :: Python :: 3.13
Classifier: Topic :: Utilities
Requires-Python: >=3.13
License-File: LICENSE.txt
Requires-Dist: capstone>=5.0.6
Requires-Dist: click>=8.2.1
Requires-Dist: keystone-engine>=0.9.2
Requires-Dist: z3-solver>=4.15.0.0
Dynamic: license-file
